{
  "workbench.colorTheme": "Min Dark",
  "workbench.iconTheme": "symbols",
  "editor.lineHeight": 1.9,
  "npm-intellisense.importES6": true,
  "npm-intellisense.importQuotes": "'",
  "npm-intellisense.importLinebreak": ";\r\n",
  "npm-intellisense.importDeclarationType": "const",
  "git.confirmSync": false,
  "explorer.confirmDragAndDrop": false,
  "git.enableSmartCommit": true,
  "explorer.confirmDelete": false,
  "editor.unicodeHighlight.invisibleCharacters": false,
  "editor.unicodeHighlight.ambiguousCharacters": false,
  "workbench.editorAssociations": {
      "*.exe": "default"
  },
  "editor.minimap.size": "fit",
  "github.copilot.enable": {
      "*": false,
      "plaintext": false,
      "markdown": false,
      "scminput": false
  },
  "editor.fontSize": 15,
  "editor.find.addExtraSpaceOnTop": false,
  "extensions.ignoreRecommendations": true,
  "workbench.startupEditor": "none",
}
